TagScriptEngine/__init__.py
TagScriptEngine/exceptions.py
TagScriptEngine/interpreter.py
TagScriptEngine/utils.py
TagScriptEngine/verb.py
TagScriptEngine/adapter/__init__.py
TagScriptEngine/adapter/discordadapters.py
TagScriptEngine/adapter/functionadapter.py
TagScriptEngine/adapter/intadapter.py
TagScriptEngine/adapter/objectadapter.py
TagScriptEngine/adapter/stringadapter.py
TagScriptEngine/block/__init__.py
TagScriptEngine/block/assign.py
TagScriptEngine/block/breakblock.py
TagScriptEngine/block/command.py
TagScriptEngine/block/control.py
TagScriptEngine/block/cooldown.py
TagScriptEngine/block/embedblock.py
TagScriptEngine/block/fiftyfifty.py
TagScriptEngine/block/helpers.py
TagScriptEngine/block/loosevariablegetter.py
TagScriptEngine/block/mathblock.py
TagScriptEngine/block/randomblock.py
TagScriptEngine/block/range.py
TagScriptEngine/block/redirect.py
TagScriptEngine/block/replaceblock.py
TagScriptEngine/block/require_blacklist.py
TagScriptEngine/block/shortcutredirect.py
TagScriptEngine/block/stopblock.py
TagScriptEngine/block/strf.py
TagScriptEngine/block/strictvariablegetter.py
TagScriptEngine/block/substr.py
TagScriptEngine/block/urlencodeblock.py
TagScriptEngine/interface/__init__.py
TagScriptEngine/interface/adapter.py
TagScriptEngine/interface/block.py
TagScript-2.6.5.dist-info/LICENSE
TagScript-2.6.5.dist-info/METADATA
TagScript-2.6.5.dist-info/WHEEL
TagScript-2.6.5.dist-info/top_level.txt
TagScript-2.6.5.dist-info/RECORD
