Metadata-Version: 2.2
Name: TagScript
Version: 2.6.5
Summary: An easy drop in user-provided Templating system.
Home-page: https://github.com/phenom4n4n/TagScript
Author: PhenoM4n4n
Author-email: noumenondiscord@gmail.com
License: Creative Commons Attribution 4.0 International License
Keywords: tagscript
Classifier: Development Status :: 5 - Production/Stable
Classifier: Intended Audience :: Developers
Classifier: License :: Freely Distributable
Classifier: Natural Language :: English
Classifier: Operating System :: OS Independent
Classifier: Programming Language :: Python :: 3.8
Requires-Python: >=3.8
License-File: LICENSE
Requires-Dist: discord.py==2.2.3
Requires-Dist: pyparsing
